ai_commit_generator/__init__.py
ai_commit_generator/api_clients.py
ai_commit_generator/cli.py
ai_commit_generator/config.py
ai_commit_generator/core.py
ai_commit_generator/git_hook.py
joshi_ai_commits-1.0.0.dist-info/licenses/LICENSE
joshi_ai_commits-1.0.0.dist-info/METADATA
joshi_ai_commits-1.0.0.dist-info/WHEEL
joshi_ai_commits-1.0.0.dist-info/entry_points.txt
joshi_ai_commits-1.0.0.dist-info/top_level.txt
joshi_ai_commits-1.0.0.dist-info/RECORD
