Metadata-Version: 2.4
Name: joshi-ai-commits
Version: 1.0.0
Summary: AI-powered Git commit message generator that automatically creates conventional commit messages using Groq, OpenRouter, or Cohere APIs
Author-email: Joshi <joshi@nuox.io>
License-Expression: MIT
Project-URL: Homepage, https://github.com/Joshi-e8/ai-commit-generator
Project-URL: Repository, https://github.com/Joshi-e8/ai-commit-generator.git
Project-URL: Issues, https://github.com/Joshi-e8/ai-commit-generator/issues
Project-URL: Documentation, https://github.com/Joshi-e8/ai-commit-generator#readme
Project-URL: Changelog, https://github.com/Joshi-e8/ai-commit-generator/releases
Project-URL: Bug Reports, https://github.com/Joshi-e8/ai-commit-generator/issues
Project-URL: Feature Requests, https://github.com/Joshi-e8/ai-commit-generator/issues
Project-URL: Source Code, https://github.com/Joshi-e8/ai-commit-generator
Keywords: git,commit,ai,conventional-commits,automation,groq,openrouter,cohere,llama,claude,gpt,developer-tools,productivity,git-hooks,commit-messages,machine-learning,natural-language-processing,cli
Classifier: Development Status :: 5 - Production/Stable
Classifier: Environment :: Console
Classifier: Intended Audience :: Developers
Classifier: Intended Audience :: Information Technology
Classifier: Operating System :: OS Independent
Classifier: Programming Language :: Python :: 3
Classifier: Programming Language :: Python :: 3.8
Classifier: Programming Language :: Python :: 3.9
Classifier: Programming Language :: Python :: 3.10
Classifier: Programming Language :: Python :: 3.11
Classifier: Programming Language :: Python :: 3.12
Classifier: Programming Language :: Python :: 3.13
Classifier: Topic :: Software Development :: Version Control :: Git
Classifier: Topic :: Software Development :: Libraries :: Python Modules
Classifier: Topic :: Software Development :: Quality Assurance
Classifier: Topic :: Utilities
Classifier: Topic :: Text Processing :: Linguistic
Classifier: Topic :: Scientific/Engineering :: Artificial Intelligence
Classifier: Typing :: Typed
Requires-Python: >=3.8
License-File: LICENSE
Requires-Dist: click>=8.0.0
Requires-Dist: requests>=2.25.0
Requires-Dist: pyyaml>=6.0
Requires-Dist: python-dotenv>=0.19.0
Requires-Dist: rich>=12.0.0
Requires-Dist: setuptools>=61.0
Provides-Extra: dev
Requires-Dist: pytest>=7.0.0; extra == "dev"
Requires-Dist: pytest-cov>=4.0.0; extra == "dev"
Requires-Dist: black>=22.0.0; extra == "dev"
Requires-Dist: mypy>=1.0.0; extra == "dev"
Requires-Dist: types-requests; extra == "dev"
Requires-Dist: types-PyYAML; extra == "dev"
Dynamic: license-file
